{
  "id": 2776732,
  "url": "https://gitee.com/api/v5/repos/jfinal/jfinal/pulls/58",
  "html_url": "https://gitee.com/jfinal/jfinal/pulls/58",
  "diff_url": "https://gitee.com/jfinal/jfinal/pulls/58.diff",
  "patch_url": "https://gitee.com/jfinal/jfinal/pulls/58.patch",
  "issue_url": "https://gitee.com/api/v5/repos/jfinal/jfinal/issues/58",
  "commits_url": "https://gitee.com/api/v5/repos/jfinal/jfinal/pulls/58/commits",
  "review_comments_url": "https://gitee.com/api/v5/repos/jfinal/jfinal/pulls/comments/{/number}",
  "review_comment_url": "https://gitee.com/api/v5/repos/jfinal/jfinal/pulls/comments",
  "comments_url": "https://gitee.com/api/v5/repos/jfinal/jfinal/58/comments",
  "statuses_url": "https://gitee.com/api/v5/repos/jfinal/jfinal/12cda4ae5e7d2d4a7595f3ef90cf06efb9fbc1be",
  "number": 58,
  "state": "closed",
  "title": "【轻量级 PR】：change find private to protected",
  "body": null,
  "assignees_number": 0,
  "testers_number": 0,
  "assignees": [],
  "testers": [],
  "milestone": null,
  "labels": [],
  "locked": false,
  "created_at": "2020-09-01T18:49:05+08:00",
  "updated_at": "2020-09-03T16:59:12+08:00",
  "closed_at": "2020-09-02T15:40:01+08:00",
  "merged_at": null,
  "mergeable": false,
  "can_merge_check": false,
  "head": "$head",
  "base": "$base",
  "_links": "$links",
  "user": "$user"
}